flytekitplugins_ray-1.16.12-py3.14-nspkg.pth
flytekitplugins/ray/__init__.py
flytekitplugins/ray/models.py
flytekitplugins/ray/task.py
flytekitplugins_ray-1.16.12.dist-info/METADATA
flytekitplugins_ray-1.16.12.dist-info/WHEEL
flytekitplugins_ray-1.16.12.dist-info/namespace_packages.txt
flytekitplugins_ray-1.16.12.dist-info/top_level.txt
flytekitplugins_ray-1.16.12.dist-info/RECORD
